{
  "config": {
    "n": 3000,
    "feature_dim": 10,
    "num_labels": 30,
    "radius": null,
    "radii_file": null,
    "radius_range": null,
    "center_spread": 1.0,
    "irrelevant_features": 10,
    "sampling": "from_spheres",
    "label_noise": 0.05,
    "seed": 115079,
    "out": "data\\synthetic\\exp12_li_sweep\\candidates\\h0.4_c07_raw"
  },
  "summary": {
    "n": 3000,
    "feature_dim_total": 20,
    "feature_dim_relevant": 10,
    "num_labels": 30,
    "l_mean": 5.947666666666667,
    "l_min": 0,
    "l_max": 19,
    "unlabeled_fraction": 0.0026666666666666666,
    "mean_radius": 0.5258441361188093,
    "min_radius": 0.13778591444278926,
    "max_radius": 0.7992905996627256
  }
}